LICENSE
README.md
setup.py
xlab/__init__.py
xlab/cache.py
xlab/cli.py
xlab/experiment.py
xlab/filesys.py
xlab/utils.py
xlab.egg-info/PKG-INFO
xlab.egg-info/SOURCES.txt
xlab.egg-info/dependency_links.txt
xlab.egg-info/entry_points.txt
xlab.egg-info/requires.txt
xlab.egg-info/top_level.txt